{"nodes": [{"id": "operational_agent_guide", "label": "Operational Agent Guide", "file_type": "document", "source_file": "AGENTS.md", "source_location": null, "source_url": null, "captured_at": null, "author": null, "contributor": null}, {"id": "tenant_isolation_rules", "label": "Tenant Isolation Rules", "file_type": "document", "source_file": "AGENTS.md", "source_location": null, "source_url": null, "captured_at": null, "author": null, "contributor": null}], "edges": [{"source": "operational_agent_guide", "target": "tenant_isolation_rules", "relation": "rationale_for", "confidence": "EXTRACTED", "confidence_score": 1.0, "source_file": "AGENTS.md", "source_location": null, "weight": 1.0}, {"source": "operational_agent_guide", "target": "minimal_context_editing", "relation": "rationale_for", "confidence": "EXTRACTED", "confidence_score": 1.0, "source_file": "AGENTS.md", "source_location": null, "weight": 1.0}, {"source": "operational_agent_guide", "target": "app_module_domain_registration", "relation": "rationale_for", "confidence": "EXTRACTED", "confidence_score": 1.0, "source_file": "AGENTS.md", "source_location": null, "weight": 1.0}], "hyperedges": [{"id": "workspace_crm_surface", "label": "Workspace CRM Surface", "nodes": ["contacts_module", "contacts_controller_workspace_scoped_contacts", "contacts_service_import_and_tagging", "conversations_controller_workspace_scoped_conversations", "conversations_service_access_control"], "relation": "form", "confidence": "INFERRED", "confidence_score": 0.9, "source_file": "AGENTS.md"}]}